btrfsmaint
