Metadata-Version: 1.1
Name: btrfsmaint
Version: 0.5.2
Summary: BTRFS Filesystem Maintenace Scripts.
Home-page: https://github.com/joshland/btrfsmaint
Author: Joshua M. Schmidlkofer
Author-email: joshland@gmail.com
License: Apache 2.0
Keywords: btrfs maintenance administration
Platform: any
Classifier: Development Status :: 4 - Beta
Classifier: Intended Audience :: System Administrators
Classifier: Topic :: System :: Filesystems
Classifier: License :: OSI Approved :: Apache Software License
Classifier: Programming Language :: Python :: 2.6
Classifier: Programming Language :: Python :: 2.7
Classifier: Programming Language :: Python :: 3
Classifier: Programming Language :: Python :: 3.3
Classifier: Programming Language :: Python :: 3.4
Classifier: Programming Language :: Python :: 3.5
Classifier: Programming Language :: Python :: 3.6
